persian_sms_manager/__init__.py
persian_sms_manager/base.py
persian_sms_manager/ippanel.py
persian_sms_manager/manager.py
persian_sms_manager/raygansms.py
persian_sms_manager-2.1.1.dist-info/licenses/LICENSE.txt
persian_sms_manager-2.1.1.dist-info/METADATA
persian_sms_manager-2.1.1.dist-info/WHEEL
persian_sms_manager-2.1.1.dist-info/top_level.txt
persian_sms_manager-2.1.1.dist-info/RECORD
