Metadata-Version: 2.4
Name: persian_sms_manager
Version: 2.1.1
Summary: A package for managing Iranian SMS services
Home-page: https://github.com/AAbbasRR/persianSMSManager.git
Author: Abbas Rahimzadeh
Author-email: arahimzadeh@gmail.com
Classifier: Programming Language :: Python :: 3
Classifier: License :: OSI Approved :: MIT License
Classifier: Operating System :: OS Independent
License-File: LICENSE.txt
Requires-Dist: requests
Dynamic: author
Dynamic: author-email
Dynamic: classifier
Dynamic: description
Dynamic: description-content-type
Dynamic: home-page
Dynamic: license-file
Dynamic: requires-dist
Dynamic: summary
